batchtk/algos/__init__.py
batchtk/algos/optuna_utils.py
batchtk/algos/search_shims.py
batchtk/algos/smac_utils.py
batchtk/header/__init__.py
batchtk/header/header.py
batchtk/inspyredtk/__init__.py
batchtk/inspyredtk/search.py
batchtk/raytk/__init__.py
batchtk/raytk/search.py
batchtk/runtk/__init__.py
batchtk/runtk/dispatchers.py
batchtk/runtk/runners.py
batchtk/runtk/sockets.py
batchtk/runtk/submits.py
batchtk/runtk/trial.py
batchtk/runtk/util_class.py
batchtk/sshtk/__init__.py
batchtk/sshtk/utils.py
batchtk/utils/__init__.py
batchtk/utils/debug.py
batchtk/utils/misc.py
batchtk/utils/serializer.py
batchtk/utils/storage.py
batchtk/utils/utils.py
batchtk/utils/version.py
batchtk-0.1.6.dist-info/licenses/LICENSE.md
batchtk-0.1.6.dist-info/METADATA
batchtk-0.1.6.dist-info/WHEEL
batchtk-0.1.6.dist-info/top_level.txt
batchtk-0.1.6.dist-info/RECORD
