Metadata-Version: 2.4
Name: batchtk
Version: 0.1.6
Summary: Batch submission toolkit for Python
Author-email: James Chen <jchen.6727@gmail.com>
License-File: LICENSE.md
Requires-Dist: importlib-metadata; python_version > "3"
Requires-Dist: numpy
Requires-Dist: pandas
Requires-Dist: filelock
Provides-Extra: ssh
Requires-Dist: fabric>3; extra == "ssh"
Provides-Extra: test
Requires-Dist: python-dotenv>1; extra == "test"
Requires-Dist: pytest>7; extra == "test"
Dynamic: license-file
